LICENSE
README.rst
numba_quaternion/__init__.py
numba_quaternion-0.2.0.dist-info/LICENSE
numba_quaternion-0.2.0.dist-info/WHEEL
numba_quaternion-0.2.0.dist-info/METADATA
numba_quaternion-0.2.0.dist-info/RECORD
