Metadata-Version: 2.1
Name: numba-quaternion
Version: 0.2.0
Summary: Some convenience functions for Cosmology-related analysis.
Home-page: https://github.com/ickc/numba_quaternion
License: BSD-3-Clause
Keywords: cosmology,CMB
Author: Kolen Cheung
Author-email: christian.kolen@gmail.com
Requires-Python: >=3.8
Classifier: Development Status :: 4 - Beta
Classifier: Environment :: Console
Classifier: Intended Audience :: Developers
Classifier: License :: OSI Approved :: BSD License
Classifier: Operating System :: Microsoft :: Windows
Classifier: Operating System :: POSIX
Classifier: Operating System :: Unix
Classifier: Programming Language :: Python
Classifier: Programming Language :: Python :: 3
Classifier: Programming Language :: Python :: 3.8
Classifier: Programming Language :: Python :: 3.9
Classifier: Programming Language :: Python :: Implementation :: CPython
Classifier: Topic :: Software Development :: Build Tools
Classifier: Topic :: Utilities
Provides-Extra: docs
Provides-Extra: extras
Provides-Extra: tests
Requires-Dist: coloredlogs (>=14,<16); extra == "extras"
Requires-Dist: coverage; extra == "tests"
Requires-Dist: coveralls; extra == "tests"
Requires-Dist: flake8; extra == "tests"
Requires-Dist: numba (>=0.52)
Requires-Dist: numpy (>=1,<2)
Requires-Dist: pygments-style-solarized; extra == "docs"
Requires-Dist: pytest-cov; extra == "tests"
Requires-Dist: pytest-parallel; extra == "tests"
Requires-Dist: pytest; extra == "tests"
Requires-Dist: sphinx (>=3.3,<4.0); extra == "docs"
Requires-Dist: sphinx-bootstrap-theme; extra == "docs"
Requires-Dist: sphinxcontrib-apidoc; extra == "docs"
Project-URL: Documentation, https://ickc.github.io/numba_quaternion
Project-URL: Repository, https://github.com/ickc/numba_quaternion
